Fallen/Fallen.py
Fallen/__init__.py
fallen-1.0.0.dist-info/METADATA
fallen-1.0.0.dist-info/WHEEL
fallen-1.0.0.dist-info/top_level.txt
fallen-1.0.0.dist-info/RECORD
