Metadata-Version: 2.1
Name: fallen
Version: 1.0.0
Summary: Fallen Financial Tools - Tools for Argentinian Market 
Home-page: https://github.com/franco-lamas/Fallen
Author: Franco Lamas, Marcelo Colon
Author-email: francomlamas@gmail.com
License: Apache
Keywords: pandas,online,historical,downloader,finance
Platform: any
Classifier: License :: OSI Approved :: Apache Software License
Classifier: Development Status :: 3 - Alpha
Classifier: Operating System :: OS Independent
Classifier: Intended Audience :: Developers
Classifier: Topic :: Office/Business :: Financial
Classifier: Topic :: Office/Business :: Financial :: Investment
Classifier: Topic :: Scientific/Engineering :: Interface Engine/Protocol Translator
Classifier: Topic :: Software Development :: Libraries
Classifier: Topic :: Software Development :: Libraries :: Python Modules
Classifier: Programming Language :: Python :: 3
Classifier: Programming Language :: Python :: 3.8
Classifier: Programming Language :: Python :: 3.9
Classifier: Programming Language :: Python :: 3.10
Classifier: Programming Language :: Python :: 3.11
